{
  "project_info": {
    "project_number": "414243187304",
    "project_id": "remitngo-6bd71",
    "storage_bucket": "remitngo-6bd71.appspot.com"
  },
  "client": [
    {
      "client_info": {
        "mobilesdk_app_id": "1:414243187304:android:0a0e76a9feb992190369dd",
        "android_client_info": {
          "package_name": "com.bsel.remitngo"
        }
      },
      "oauth_client": [],
      "api_key": [
        {
          "current_key": "AIzaSyBq68cwQW2fepYLDCEk-ll08VJtse26gjs"
        }
      ],
      "services": {
        "appinvite_service": {
          "other_platform_oauth_client": []
        }
      }
    }
  ],
  "configuration_version": "1"
}